setup.py
fabuild/__init__.py
fabuild/clean.py
fabuild/coffee.py
fabuild/concat.py
fabuild/fabfile.py
fabuild/jade.py
fabuild/live_reload.py
fabuild/stylus.py
fabuild/test.py
fabuild/util.py
fabuild/watch.py
fabuild.egg-info/PKG-INFO
fabuild.egg-info/SOURCES.txt
fabuild.egg-info/dependency_links.txt
fabuild.egg-info/not-zip-safe
fabuild.egg-info/requires.txt
fabuild.egg-info/top_level.txt
fabuild/monkey/__init__.py
fabuild/monkey/livereload_forcehandler.py