Metadata-Version: 1.1
Name: fabuild
Version: 0.0.14
Summary: Script-based build system build on top of Fabric
Home-page: https://github.com/johnnadratowski/fabuild
Author: John Nadratowski
Author-email: jnadro52@gmail.com
License: UNKNOWN
Platform: UNKNOWN
Classifier: Intended Audience :: Developers
Classifier: Intended Audience :: System Administrators
Classifier: Operating System :: OS Independent
Classifier: Topic :: Software Development
